qcom/__init__.py
qcom/lattice_register.py
qcom/_internal/__init__.py
qcom/_internal/progress.py
qcom/controls/__init__.py
qcom/controls/time_series.py
qcom/controls/adapters/__init__.py
qcom/controls/adapters/base.py
qcom/controls/adapters/ising.py
qcom/controls/adapters/rydberg.py
qcom/data/__init__.py
qcom/data/noise.py
qcom/data/ops.py
qcom/data/sampling.py
qcom/hamiltonians/__init__.py
qcom/hamiltonians/base.py
qcom/hamiltonians/ising.py
qcom/hamiltonians/rydberg.py
qcom/io/__init__.py
qcom/io/aquila.py
qcom/io/parquet.py
qcom/io/text.py
qcom/metrics/__init__.py
qcom/metrics/bitstrings.py
qcom/metrics/classical.py
qcom/metrics/entanglement.py
qcom/metrics/probabilities.py
qcom/metrics/states.py
qcom/solvers/__init__.py
qcom/solvers/dynamic.py
qcom/solvers/static.py
qcom-0.2.1.dist-info/licenses/LICENSE.txt
qcom-0.2.1.dist-info/METADATA
qcom-0.2.1.dist-info/WHEEL
qcom-0.2.1.dist-info/top_level.txt
qcom-0.2.1.dist-info/RECORD
