Metadata-Version: 2.4
Name: QCOM
Version: 0.2.1
Summary: Quantum Computation Library
Author-email: Avi Kaufman <avigkaufman@gmail.com>
License: MIT License
Project-URL: Homepage, https://github.com/AviKaufman/QCOM
Project-URL: Source, https://github.com/AviKaufman/QCOM
Project-URL: Issues, https://github.com/AviKaufman/QCOM/issues
Classifier: Development Status :: 3 - Alpha
Classifier: Intended Audience :: Science/Research
Classifier: License :: OSI Approved :: MIT License
Classifier: Programming Language :: Python :: 3
Classifier: Programming Language :: Python :: 3 :: Only
Classifier: Programming Language :: Python :: 3.8
Classifier: Programming Language :: Python :: 3.9
Classifier: Programming Language :: Python :: 3.10
Classifier: Programming Language :: Python :: 3.11
Classifier: Programming Language :: Python :: 3.12
Classifier: Topic :: Scientific/Engineering :: Physics
Classifier: Topic :: Scientific/Engineering :: Information Analysis
Requires-Python: >=3.8
License-File: LICENSE.txt
Requires-Dist: numpy>=1.23
Requires-Dist: scipy>=1.10
Requires-Dist: pandas>=1.5
Provides-Extra: parquet
Requires-Dist: pyarrow>=10; extra == "parquet"
Provides-Extra: mitigation
Requires-Dist: mthree>=2.0; extra == "mitigation"
Provides-Extra: viz
Requires-Dist: matplotlib>=3.6; extra == "viz"
Provides-Extra: dev
Requires-Dist: pytest>=7.0; extra == "dev"
Requires-Dist: pytest-cov>=4.0; extra == "dev"
Requires-Dist: ruff>=0.4; extra == "dev"
Requires-Dist: black>=23.0; extra == "dev"
Requires-Dist: mypy>=1.0; extra == "dev"
Provides-Extra: all
Requires-Dist: QCOM[mitigation,parquet,viz]; extra == "all"
Dynamic: license-file
